pyMMAopt/__about__.py
pyMMAopt/__init__.py
pyMMAopt/constraints.py
pyMMAopt/mma.py
pyMMAopt/mma_solver.py
pyMMAopt-0.0.8.dist-info/LICENSE
pyMMAopt-0.0.8.dist-info/METADATA
pyMMAopt-0.0.8.dist-info/WHEEL
pyMMAopt-0.0.8.dist-info/top_level.txt
pyMMAopt-0.0.8.dist-info/RECORD
