Metadata-Version: 2.1
Name: pyMMAopt
Version: 0.0.8
Summary: MMA optimization algorithm in python
Home-page: https://github.com/LLNL/pyMMAopt
Author: Miguel Salazar de Troya
Author-email: salazardetro1@llnl.gov
License: License :: OSI Approved :: MIT License
Platform: any
Classifier: License :: OSI Approved :: MIT License
Classifier: Development Status :: 4 - Beta
Classifier: Operating System :: OS Independent
Classifier: Programming Language :: Python
Classifier: Programming Language :: Python :: 3
Classifier: Topic :: Scientific/Engineering
Classifier: Topic :: Scientific/Engineering :: Mathematics
Requires-Python: >=3
License-File: LICENSE
Requires-Dist: numpy
Requires-Dist: numexpr
